MANIFEST.in
README.rst
setup.cfg
setup.py
ckanext/__init__.py
ckanext/timeseries/__init__.py
ckanext/timeseries/commands.py
ckanext/timeseries/db.py
ckanext/timeseries/helpers.py
ckanext/timeseries/interfaces.py
ckanext/timeseries/plugin.py
ckanext/timeseries/controller/__init__.py
ckanext/timeseries/controller/datastore_ts.py
ckanext/timeseries/controller/resource_controller.py
ckanext/timeseries/logic/__init__.py
ckanext/timeseries/logic/action.py
ckanext/timeseries/logic/auth.py
ckanext/timeseries/logic/schema.py
ckanext/timeseries/tests/__init__.py
ckanext/timeseries/tests/helpers.py
ckanext/timeseries/tests/resetdb.py
ckanext/timeseries/tests/sample_timeseries_plugin.py
ckanext/timeseries/tests/skipped_test_dump_.py
ckanext/timeseries/tests/skipped_test_interface.py
ckanext/timeseries/tests/test_commands.py
ckanext/timeseries/tests/test_create.py
ckanext/timeseries/tests/test_create_short.py
ckanext/timeseries/tests/test_db.py
ckanext/timeseries/tests/test_delete.py
ckanext/timeseries/tests/test_dump.py
ckanext/timeseries/tests/test_helpers.py
ckanext/timeseries/tests/test_info.py
ckanext/timeseries/tests/test_plugin.py
ckanext/timeseries/tests/test_retention.py
ckanext/timeseries/tests/test_search.py
ckanext/timeseries/tests/test_search_short.py
ckanext/timeseries/tests/test_search_timeseries.py
ckanext/timeseries/tests/test_unit.py
ckanext/timeseries/tests/test_upsert.py
ckanext/timeseries/tests/test_upsert_short.py
ckanext_timeseries.egg-info/PKG-INFO
ckanext_timeseries.egg-info/SOURCES.txt
ckanext_timeseries.egg-info/dependency_links.txt
ckanext_timeseries.egg-info/entry_points.txt
ckanext_timeseries.egg-info/namespace_packages.txt
ckanext_timeseries.egg-info/pbr.json
ckanext_timeseries.egg-info/requires.txt
ckanext_timeseries.egg-info/top_level.txt