Metadata-Version: 1.1
Name: ckanext-timeseries
Version: 1.2.0
Summary: Timeseries-based datastore extension
Home-page: https://github.com/namgk/ckan-timeseries
Author: Nam Giang
Author-email: kyng@ece.ubc.ca
License: AGPL
Keywords: CKAN
Platform: UNKNOWN
Classifier: Development Status :: 4 - Beta
Classifier: License :: OSI Approved :: GNU Affero General Public License v3 or later (AGPLv3+)
Classifier: Programming Language :: Python :: 2.6
Classifier: Programming Language :: Python :: 2.7
